{"Eld":[{"name":"El","type":"rune","quantity":"3"}],"Tir":[{"name":"Eld","type":"rune","quantity":"3"}],"Nef":[{"name":"Tir","type":"rune","quantity":"3"}],"Eth":[{"name":"Nef","type":"rune","quantity":"3"}],"Ith":[{"name":"Eth","type":"rune","quantity":"3"}],"Tal":[{"name":"Ith","type":"rune","quantity":"3"}],"Ral":[{"name":"Tal","type":"rune","quantity":"3"}],"Ort":[{"name":"Ral","type":"rune","quantity":"3"}],"Thul":[{"name":"Ort","type":"rune","quantity":"3"}],"Amn":[{"name":"Thul","type":"rune","quantity":"3"},{"name":"Chipped Topaz","type":"gem","quantity":"1"}],"Sol":[{"name":"Amn","type":"rune","quantity":"3"},{"name":"Chipped Amethyst","type":"gem","quantity":"1"}],"Shael":[{"name":"Sol","type":"rune","quantity":"3"},{"name":"Chipped Sapphire","type":"gem","quantity":"1"}],"Dol":[{"name":"Shael","type":"rune","quantity":"3"},{"name":"Chipped Ruby","type":"gem","quantity":"1"}],"Hel":[{"name":"Dol","type":"rune","quantity":"3"},{"name":"Chipped Emerald","type":"gem","quantity":"1"}],"Io":[{"name":"Hel","type":"rune","quantity":"3"},{"name":"Chipped Diamond","type":"gem","quantity":"1"}],"Lum":[{"name":"Io","type":"rune","quantity":"3"},{"name":"Flawed Topaz","type":"gem","quantity":"1"}],"Ko":[{"name":"Lum","type":"rune","quantity":"3"},{"name":"Flawed Amethyst","type":"gem","quantity":"1"}],"Fal":[{"name":"Ko","type":"rune","quantity":"3"},{"name":"Flawed Sapphire","type":"gem","quantity":"1"}],"Lem":[{"name":"Fal","type":"rune","quantity":"3"},{"name":"Flawed Ruby","type":"gem","quantity":"1"}],"Pul":[{"name":"Lem","type":"rune","quantity":"3"},{"name":"Flawed Emerald","type":"gem","quantity":"1"}],"Um":[{"name":"Pul","type":"rune","quantity":"2"},{"name":"Flawed Diamond","type":"gem","quantity":"1"}],"Mal":[{"name":"Um","type":"rune","quantity":"2"},{"name":"Topaz","type":"gem","quantity":"1"}],"Ist":[{"name":"Mal","type":"rune","quantity":"2"},{"name":"Amethyst","type":"gem","quantity":"1"}],"Gul":[{"name":"Ist","type":"rune","quantity":"2"},{"name":"Sapphire","type":"gem","quantity":"1"}],"Vex":[{"name":"Gul","type":"rune","quantity":"2"},{"name":"Ruby","type":"gem","quantity":"1"}],"Ohm":[{"name":"Vex","type":"rune","quantity":"2"},{"name":"Emerald","type":"gem","quantity":"1"}],"Lo":[{"name":"Ohm","type":"rune","quantity":"2"},{"name":"Diamond","type":"gem","quantity":"1"}],"Sur":[{"name":"Lo","type":"rune","quantity":"2"},{"name":"Flawless Topaz","type":"gem","quantity":"1"}],"Ber":[{"name":"Sur","type":"rune","quantity":"2"},{"name":"Flawless Amethyst","type":"gem","quantity":"1"}],"Jah":[{"name":"Ber","type":"rune","quantity":"2"},{"name":"Flawless Sapphire","type":"gem","quantity":"1"}],"Cham":[{"name":"Jah","type":"rune","quantity":"2"},{"name":"Flawless Ruby","type":"gem","quantity":"1"}],"Zod":[{"name":"Cham","type":"rune","quantity":"2"},{"name":"Flawless Emerald","type":"gem","quantity":"1"}]}